plugs_media/__init__.py
plugs_media/apps.py
plugs_media/exceptions.py
plugs_media/fields.py
plugs_media/models.py
plugs_media/permissions.py
plugs_media/serializers.py
plugs_media/settings.py
plugs_media/urls.py
plugs_media/validators.py
plugs_media/views.py
plugs_media/widgets.py
plugs_media/management/__init__.py
plugs_media/management/commands/__init__.py
plugs_media/management/commands/delete_unused_media.py
plugs_media/migrations/0001_initial.py
plugs_media/migrations/0002_auto_20170107_1957.py
plugs_media/migrations/0003_auto_20170109_2240.py
plugs_media/migrations/0004_auto_20170109_2246.py
plugs_media/migrations/0005_auto_20170109_2258.py
plugs_media/migrations/0006_auto_20170109_2259.py
plugs_media/migrations/0007_media_user.py
plugs_media/migrations/0008_mediacontenttype.py
plugs_media/migrations/0009_auto_20170212_1748.py
plugs_media/migrations/0010_auto_20170814_1627.py
plugs_media/migrations/0011_auto_20170913_2144.py
plugs_media/migrations/0012_auto_20190416_1111.py
plugs_media/migrations/__init__.py
plugs_media/static/css/plugs_media.css
plugs_media/static/js/plugs_media.js
plugs_media/templates/plugs_media/base.html
plugs_media-0.2.2.dist-info/AUTHORS.rst
plugs_media-0.2.2.dist-info/LICENSE
plugs_media-0.2.2.dist-info/METADATA
plugs_media-0.2.2.dist-info/WHEEL
plugs_media-0.2.2.dist-info/top_level.txt
plugs_media-0.2.2.dist-info/RECORD
