Metadata-Version: 2.1
Name: plugs-media
Version: 0.2.2
Summary: Reusable APP to deal with file uploads
Home-page: https://github.com/solocompt/plugs-media
Author: Solo
Author-email: geral@solo.com.pt
License: MIT
Keywords: plugs-media
Platform: UNKNOWN
Classifier: Development Status :: 3 - Alpha
Classifier: Framework :: Django :: 1.11
Classifier: Intended Audience :: Developers
Classifier: License :: OSI Approved :: MIT License
Classifier: Natural Language :: English
Classifier: Programming Language :: Python :: 3
Requires-Dist: plugs-core (<1.0.0,>=0.1.6)
Requires-Dist: python-magic (>=0.4.13)
